{
  "type_description_msg": {
    "type_description": {
      "type_name": "ros2_robot_middleware/srv/SetParam_Request",
      "fields": [
        {
          "name": "param_name",
          "type": {
            "type_id": 17,
            "capacity": 0,
            "string_capacity": 0,
            "nested_type_name": ""
          },
          "default_value": ""
        },
        {
          "name": "value",
          "type": {
            "type_id": 11,
            "capacity": 0,
            "string_capacity": 0,
            "nested_type_name": ""
          },
          "default_value": ""
        }
      ]
    },
    "referenced_type_descriptions": []
  },
  "type_hashes": [
    {
      "type_name": "ros2_robot_middleware/srv/SetParam_Request",
      "hash_string": "RIHS01_d1c2794028e62a81f7b58c54f429684994b89e2d1c5dac2bbc489b388cf0daa5"
    }
  ]
}